pychipbuilder-1.0.1.dist-info/top_level.txt
pychipbuilder-1.0.1.dist-info/zOH_License_v1.txt
pychipbuilder-1.0.1.dist-info/entry_points.txt
pychipbuilder-1.0.1.dist-info/WHEEL
pychipbuilder-1.0.1.dist-info/METADATA
pychipbuilder-1.0.1.dist-info/RECORD
chipbuilder/__init__.py
chipbuilder/smartfabric/exceptions.py
chipbuilder/smartfabric/host.py
chipbuilder/smartfabric/tgrid.py
chipbuilder/smartfabric/util.py
chipbuilder/smartfabric/pmic.py
chipbuilder/smartfabric/czip.cpython-37m-x86_64-linux-gnu.so
chipbuilder/smartfabric/otp.py
chipbuilder/smartfabric/__init__.py
chipbuilder/smartfabric/led.py
chipbuilder/smartfabric/data/cli_config.json
chipbuilder/smartfabric/scripts/sf_get_chipid.py
chipbuilder/smartfabric/scripts/sf_otp_program.py
chipbuilder/smartfabric/scripts/sfabric.py
chipbuilder/smartfabric/scripts/__init__.py
chipbuilder/smartfabric/scripts/sf_program_compare.py
chipbuilder/smartfabric/scripts/sf_blinky.py
chipbuilder/smartfabric/scripts/sf_dmm_vmeas.py
