Metadata-Version: 2.1
Name: pychipbuilder
Version: 1.0.1
Summary: ChipBuilder Python package for creating, designing, and interfacing with zGlue ZIPs.
Home-page: https://github.com/zglue/pychipbuilder
Author: Jorge L. Rojas
Author-email: jorge@zglue.com
License: UNKNOWN
Platform: UNKNOWN
Classifier: Intended Audience :: End Users/Desktop
Classifier: Operating System :: Microsoft :: Windows :: Windows 10
Classifier: Operating System :: POSIX :: Linux
Classifier: Operating System :: MacOS :: MacOS X
Classifier: Programming Language :: C
Classifier: Programming Language :: Python :: 3
Classifier: Programming Language :: Python :: Implementation :: CPython
Requires-Python: >=3.5
Requires-Dist: matplotlib
Requires-Dist: pyvisa
